pdf_viewer/__init__.py
colab_pdf_viewer-0.2.dist-info/METADATA
colab_pdf_viewer-0.2.dist-info/WHEEL
colab_pdf_viewer-0.2.dist-info/top_level.txt
colab_pdf_viewer-0.2.dist-info/RECORD
